odoo/addons/product_variant_inactive/README.rst
odoo/addons/product_variant_inactive/__init__.py
odoo/addons/product_variant_inactive/__manifest__.py
odoo/addons/product_variant_inactive/data/product.product.csv
odoo/addons/product_variant_inactive/i18n/ca.po
odoo/addons/product_variant_inactive/i18n/de.po
odoo/addons/product_variant_inactive/i18n/es.po
odoo/addons/product_variant_inactive/i18n/fr.po
odoo/addons/product_variant_inactive/i18n/hr.po
odoo/addons/product_variant_inactive/i18n/it.po
odoo/addons/product_variant_inactive/i18n/product_variant_inactive.pot
odoo/addons/product_variant_inactive/i18n/sl.po
odoo/addons/product_variant_inactive/models/__init__.py
odoo/addons/product_variant_inactive/models/product_template.py
odoo/addons/product_variant_inactive/models/product_variant.py
odoo/addons/product_variant_inactive/static/description/icon.png
odoo/addons/product_variant_inactive/static/description/pvi-2.png
odoo/addons/product_variant_inactive/static/description/unactive.png
odoo/addons/product_variant_inactive/static/img/img.png
odoo/addons/product_variant_inactive/static/img/pvi_1.png
odoo/addons/product_variant_inactive/tests/__init__.py
odoo/addons/product_variant_inactive/tests/test_button.py
odoo/addons/product_variant_inactive/views/product_template_view.xml
odoo/addons/product_variant_inactive/views/product_variant_view.xml
odoo12_addon_product_variant_inactive-12.0.1.1.0.dist-info/METADATA
odoo12_addon_product_variant_inactive-12.0.1.1.0.dist-info/WHEEL
odoo12_addon_product_variant_inactive-12.0.1.1.0.dist-info/top_level.txt
odoo12_addon_product_variant_inactive-12.0.1.1.0.dist-info/RECORD
